pycfurlscannercli/__init__.py
pycfurlscannercli/pycfurlscannercli.py
pycfurlscannercli/requirements.txt
pycfurlscannercli-1.2.dist-info/METADATA
pycfurlscannercli-1.2.dist-info/WHEEL
pycfurlscannercli-1.2.dist-info/entry_points.txt
pycfurlscannercli-1.2.dist-info/top_level.txt
pycfurlscannercli-1.2.dist-info/RECORD
