Metadata-Version: 2.4
Name: pycfurlscannercli
Version: 1.2
Summary: A simple Python script to interact with Cloudflare Radar URL scanner APIs from CLI.
Author-email: tdebize@mail.com
License-Expression: LGPL-3.0-or-later
Project-URL: Homepage, https://github.com/maaaaz/pycfurlscannercli
Keywords: cloudflare,radar,url,scanner,phishing,website,threat,ioc,api,cli
Classifier: Topic :: Security
Classifier: Programming Language :: Python :: 3
Requires-Python: >=3
Requires-Dist: cloudflare
Requires-Dist: validators
